[
   {
      "files" : [
         "+enet_fs.c -> enet_fs.c",
         "+enet_fs.h -> enet_fs.h",
         "+enet_fsdata.h -> enet_fsdata.h",
         "+enet_lwip.c -> enet_lwip.c",
         "+enet_lwip_ccs.cmd -> enet_lwip_ccs.cmd",
         "+fs/404.htm -> fs/404.htm",
         "+fs/about.htm -> fs/about.htm",
         "+fs/block.htm -> fs/block.htm",
         "+fs/block_tm4c129e.jpg -> fs/block_tm4c129e.jpg",
         "+fs/ek-tm4c1294xl.jpg -> fs/ek-tm4c1294xl.jpg",
         "+fs/favicon.ico -> fs/favicon.ico",
         "+fs/index.htm -> fs/index.htm",
         "+fs/javascript.js -> fs/javascript.js",
         "+fs/overview.htm -> fs/overview.htm",
         "+fs/styles.css -> fs/styles.css",
         "+fs/ti.jpg -> fs/ti.jpg",
         "+fs/tm4c.jpg -> fs/tm4c.jpg",
         "+lwipopts.h -> lwipopts.h",
         "+startup_ccs.c -> startup_ccs.c",
         "+../../../../examples/boards/ek-tm4c129exl/drivers/pinout.c -> drivers/pinout.c",
         "+../../../../third_party/fatfs/port/mmc-ek-tm4c1294xl.c -> third_party/fatfs/port/mmc-ek-tm4c1294xl.c",
         "+../../../../third_party/fatfs/src/ff.c -> third_party/fatfs/src/ff.c",
         "+../../../../third_party/lwip-1.4.1/apps/httpserver_raw/httpd.c -> third_party/lwip-1.4.1/apps/httpserver_raw/httpd.c",
         "+../../../../utils/locator.c -> utils/locator.c",
         "+../../../../utils/lwiplib.c -> utils/lwiplib.c",
         "+../../../../utils/uartstdio.c -> utils/uartstdio.c",
         "+../../../../utils/ustdlib.c -> utils/ustdlib.c"
      ],
      "name" : "na",
      "packages" : [],
      "default" : "na",
      "compiler" : {
         "effective" : "na",
         "location" : "na",
         "specified" : "na"
      }
   }
]
